{
  "date": "2026-05-29",
  "scan_time": "12:36:28",
  "latest_t86": "20260529",
  "scanned": 418,
  "signals_count": 10,
  "strong": [
    {
      "code": "6235",
      "name": "華孚",
      "price": 44.25,
      "change_pct": 0.91,
      "volume_ratio": 8.46,
      "streak": 6,
      "cum_buy": 837,
      "in_top30": false,
      "in_module_a": false,
      "strength": 70,
      "reasons": [
        "連買6天",
        "量比8.5x(爆量)",
        "今日+0.9%(微漲)"
      ]
    },
    {
      "code": "2428",
      "name": "興勤",
      "price": 294.0,
      "change_pct": 0.51,
      "volume_ratio": 3.35,
      "streak": 7,
      "cum_buy": 1973,
      "in_top30": false,
      "in_module_a": false,
      "strength": 70,
      "reasons": [
        "連買7天",
        "量比3.3x(爆量)",
        "今日+0.5%(微漲)"
      ]
    },
    {
      "code": "2369",
      "name": "菱生",
      "price": 41.1,
      "change_pct": 3.4,
      "volume_ratio": 2.05,
      "streak": 9,
      "cum_buy": 31971,
      "in_top30": false,
      "in_module_a": false,
      "strength": 60,
      "reasons": [
        "連買9天",
        "量比2.0x(放量)",
        "累計31K"
      ]
    },
    {
      "code": "1339",
      "name": "昭輝",
      "price": 45.7,
      "change_pct": 1.9,
      "volume_ratio": 8.62,
      "streak": 7,
      "cum_buy": 127,
      "in_top30": false,
      "in_module_a": false,
      "strength": 60,
      "reasons": [
        "連買7天",
        "量比8.6x(爆量)"
      ]
    }
  ],
  "moderate": [
    {
      "code": "1597",
      "name": "直得",
      "price": 180.5,
      "change_pct": 0.0,
      "volume_ratio": 1.28,
      "streak": 7,
      "cum_buy": 1341,
      "in_top30": false,
      "in_module_a": false,
      "strength": 55,
      "reasons": [
        "連買7天",
        "量比1.3x",
        "今日+0.0%(未反映)"
      ]
    },
    {
      "code": "2426",
      "name": "鼎元",
      "price": 81.3,
      "change_pct": 0.49,
      "volume_ratio": 1.35,
      "streak": 5,
      "cum_buy": 3854,
      "in_top30": false,
      "in_module_a": false,
      "strength": 50,
      "reasons": [
        "連買5天",
        "量比1.4x",
        "今日+0.5%(微漲)"
      ]
    },
    {
      "code": "4306",
      "name": "炎洲",
      "price": 14.0,
      "change_pct": 1.08,
      "volume_ratio": 1.46,
      "streak": 8,
      "cum_buy": 7946,
      "in_top30": false,
      "in_module_a": false,
      "strength": 40,
      "reasons": [
        "連買8天",
        "量比1.5x"
      ]
    },
    {
      "code": "2491",
      "name": "吉祥全",
      "price": 23.35,
      "change_pct": 4.71,
      "volume_ratio": 1.64,
      "streak": 5,
      "cum_buy": 805,
      "in_top30": false,
      "in_module_a": false,
      "strength": 40,
      "reasons": [
        "連買5天",
        "量比1.6x"
      ]
    },
    {
      "code": "2816",
      "name": "旺旺保",
      "price": 32.5,
      "change_pct": 1.25,
      "volume_ratio": 1.59,
      "streak": 7,
      "cum_buy": 525,
      "in_top30": false,
      "in_module_a": false,
      "strength": 40,
      "reasons": [
        "連買7天",
        "量比1.6x"
      ]
    }
  ],
  "weak_count": 1
}