{
  "date": "2026-03-25",
  "query_date": "20260325",
  "total_buy": 50,
  "total_sell": 50,
  "stocks": [
    {
      "code": "2313",
      "name": "華通",
      "foreign": 23164022,
      "trust": 814593,
      "dealer": 1668978,
      "total": 25647593,
      "close_price": 230.0,
      "daily_volume": 60388130,
      "5day_change": 0.0,
      "buy_amount": 5898946390.0,
      "daily_turnover": 13889269900.0,
      "buy_ratio": 42.471248902723104,
      "volume_rank": 1,
      "amount_rank": 2,
      "avg_rank": 1.5
    },
    {
      "code": "2367",
      "name": "2367",
      "foreign": 14535821,
      "trust": -12038,
      "dealer": 640204,
      "total": 15163987,
      "close_price": 75.1,
      "daily_volume": 111818210,
      "5day_change": -1.1842125340511924,
      "buy_amount": 1138815423.6999998,
      "daily_turnover": 8397547570.999999,
      "buy_ratio": 13.561285769106837,
      "volume_rank": 2,
      "amount_rank": 9,
      "avg_rank": 5.5
    },
    {
      "code": "2317",
      "name": "鴻海",
      "foreign": 9605035,
      "trust": -390501,
      "dealer": 1596207,
      "total": 10810741,
      "close_price": 200.0,
      "daily_volume": 42000224,
      "5day_change": -4.761904761904762,
      "buy_amount": 2162148200.0,
      "daily_turnover": 8400044800.0,
      "buy_ratio": 25.73972224529088,
      "volume_rank": 3,
      "amount_rank": 3,
      "avg_rank": 3.0
    },
    {
      "code": "2883",
      "name": "凱基金",
      "foreign": 9260530,
      "trust": -535000,
      "dealer": 1391686,
      "total": 10117216,
      "close_price": 20.35,
      "daily_volume": 44335419,
      "5day_change": -1.452780835847293,
      "buy_amount": 205885345.60000002,
      "daily_turnover": 902225776.6500001,
      "buy_ratio": 22.819714413886558,
      "volume_rank": 4,
      "amount_rank": 32,
      "avg_rank": 18.0
    },
    {
      "code": "1303",
      "name": "南亞",
      "foreign": 8393561,
      "trust": 779000,
      "dealer": 872430,
      "total": 10044991,
      "close_price": 76.0,
      "daily_volume": 50666712,
      "5day_change": -11.832943514332907,
      "buy_amount": 763419316.0,
      "daily_turnover": 3850670112.0,
      "buy_ratio": 19.825622392864176,
      "volume_rank": 5,
      "amount_rank": 12,
      "avg_rank": 8.5
    },
    {
      "code": "1605",
      "name": "華新",
      "foreign": 9381288,
      "trust": 0,
      "dealer": 268142,
      "total": 9649430,
      "close_price": 31.9,
      "daily_volume": 21378931,
      "5day_change": -5.8997103755935,
      "buy_amount": 307816817.0,
      "daily_turnover": 681987898.9,
      "buy_ratio": 45.13523150432545,
      "volume_rank": 6,
      "amount_rank": 23,
      "avg_rank": 14.5
    },
    {
      "code": "3532",
      "name": "3532",
      "foreign": 9185490,
      "trust": -142,
      "dealer": -88963,
      "total": 9096385,
      "close_price": 133.0,
      "daily_volume": 3910995,
      "5day_change": -11.627906976744185,
      "buy_amount": 1209819205.0,
      "daily_turnover": 520162335.0,
      "buy_ratio": 232.58493043330404,
      "volume_rank": 7,
      "amount_rank": 7,
      "avg_rank": 7.0
    },
    {
      "code": "2886",
      "name": "兆豐金",
      "foreign": 6899131,
      "trust": 379000,
      "dealer": 679851,
      "total": 7957982,
      "close_price": 39.15,
      "daily_volume": 24243478,
      "5day_change": -0.3816735727571982,
      "buy_amount": 311554995.3,
      "daily_turnover": 949132163.6999999,
      "buy_ratio": 32.82524891849264,
      "volume_rank": 8,
      "amount_rank": 22,
      "avg_rank": 15.0
    },
    {
      "code": "2308",
      "name": "2308",
      "foreign": 6439899,
      "trust": 196632,
      "dealer": 431006,
      "total": 7067537,
      "close_price": 1550.0,
      "daily_volume": 16400731,
      "5day_change": 5.802047781569966,
      "buy_amount": 10954682350.0,
      "daily_turnover": 25421133050.0,
      "buy_ratio": 43.09281702138764,
      "volume_rank": 9,
      "amount_rank": 1,
      "avg_rank": 5.0
    },
    {
      "code": "2002",
      "name": "中鋼",
      "foreign": 6231476,
      "trust": 28000,
      "dealer": 602667,
      "total": 6862143,
      "close_price": 19.3,
      "daily_volume": 33664457,
      "5day_change": 0.0,
      "buy_amount": 132439359.9,
      "daily_turnover": 649724020.1,
      "buy_ratio": 20.3839408430084,
      "volume_rank": 10,
      "amount_rank": 40,
      "avg_rank": 25.0
    },
    {
      "code": "3702",
      "name": "3702",
      "foreign": 7577829,
      "trust": 393401,
      "dealer": -1205248,
      "total": 6765982,
      "close_price": 95.8,
      "daily_volume": 35739018,
      "5day_change": 2.900112375820539,
      "buy_amount": 648181075.6,
      "daily_turnover": 3423797924.4,
      "buy_ratio": 18.931639364013865,
      "volume_rank": 11,
      "amount_rank": 14,
      "avg_rank": 12.5
    },
    {
      "code": "2890",
      "name": "永豐金",
      "foreign": 6959258,
      "trust": -908871,
      "dealer": 659924,
      "total": 6710311,
      "close_price": 31.85,
      "daily_volume": 20408379,
      "5day_change": -0.6240214051535906,
      "buy_amount": 213723405.35000002,
      "daily_turnover": 650006871.15,
      "buy_ratio": 32.88017632365609,
      "volume_rank": 12,
      "amount_rank": 31,
      "avg_rank": 21.5
    },
    {
      "code": "2892",
      "name": "第一金",
      "foreign": 5206429,
      "trust": 81000,
      "dealer": 806804,
      "total": 6094233,
      "close_price": 28.7,
      "daily_volume": 25805636,
      "5day_change": -0.8635578356185719,
      "buy_amount": 174904487.1,
      "daily_turnover": 740621753.1999999,
      "buy_ratio": 23.61589925549597,
      "volume_rank": 13,
      "amount_rank": 34,
      "avg_rank": 23.5
    },
    {
      "code": "8028",
      "name": "8028",
      "foreign": 5514121,
      "trust": -3040,
      "dealer": 425488,
      "total": 5936569,
      "close_price": 199.5,
      "daily_volume": 23670291,
      "5day_change": 1.2690355329949239,
      "buy_amount": 1184345515.5,
      "daily_turnover": 4722223054.5,
      "buy_ratio": 25.080253554973194,
      "volume_rank": 14,
      "amount_rank": 8,
      "avg_rank": 11.0
    },
    {
      "code": "2885",
      "name": "元大金",
      "foreign": 612636,
      "trust": 4924000,
      "dealer": 340157,
      "total": 5876793,
      "close_price": 45.85,
      "daily_volume": 27859033,
      "5day_change": 2.6875630621124964,
      "buy_amount": 269450959.05,
      "daily_turnover": 1277336663.05,
      "buy_ratio": 21.094748694256545,
      "volume_rank": 15,
      "amount_rank": 25,
      "avg_rank": 20.0
    },
    {
      "code": "2327",
      "name": "國巨",
      "foreign": 5206259,
      "trust": -2448,
      "dealer": 407845,
      "total": 5611656,
      "close_price": 260.0,
      "daily_volume": 13743781,
      "5day_change": -7.308377896613191,
      "buy_amount": 1459030560.0,
      "daily_turnover": 3573383060.0,
      "buy_ratio": 40.83051090525962,
      "volume_rank": 16,
      "amount_rank": 4,
      "avg_rank": 10.0
    },
    {
      "code": "9933",
      "name": "9933",
      "foreign": 5714663,
      "trust": 0,
      "dealer": -140242,
      "total": 5574421,
      "close_price": 39.4,
      "daily_volume": 23443973,
      "5day_change": 15.54253163905579,
      "buy_amount": 219632187.4,
      "daily_turnover": 923692536.1999999,
      "buy_ratio": 23.777629329295,
      "volume_rank": 17,
      "amount_rank": 30,
      "avg_rank": 23.5
    },
    {
      "code": "1101",
      "name": "台泥",
      "foreign": 4800457,
      "trust": -33000,
      "dealer": 636081,
      "total": 5403538,
      "close_price": 23.0,
      "daily_volume": 27414244,
      "5day_change": -6.3136427096937595,
      "buy_amount": 124281374.0,
      "daily_turnover": 630527612.0,
      "buy_ratio": 19.71069492195371,
      "volume_rank": 18,
      "amount_rank": 41,
      "avg_rank": 29.5
    },
    {
      "code": "2801",
      "name": "彰銀",
      "foreign": 4552313,
      "trust": 0,
      "dealer": 563000,
      "total": 5115313,
      "close_price": 20.7,
      "daily_volume": 13926867,
      "5day_change": -0.4807619124471926,
      "buy_amount": 105886979.1,
      "daily_turnover": 288286146.9,
      "buy_ratio": 36.72981870222499,
      "volume_rank": 19,
      "amount_rank": 43,
      "avg_rank": 31.0
    },
    {
      "code": "2891",
      "name": "中信金",
      "foreign": 3265339,
      "trust": 1301000,
      "dealer": 362837,
      "total": 4929176,
      "close_price": 52.8,
      "daily_volume": 30294426,
      "5day_change": -0.9380863173677872,
      "buy_amount": 260260492.79999998,
      "daily_turnover": 1599545692.8,
      "buy_ratio": 16.270900792112712,
      "volume_rank": 20,
      "amount_rank": 26,
      "avg_rank": 23.0
    },
    {
      "code": "2347",
      "name": "2347",
      "foreign": 4515598,
      "trust": 242355,
      "dealer": 46821,
      "total": 4804774,
      "close_price": 79.9,
      "daily_volume": 9174076,
      "5day_change": -0.12499809265136719,
      "buy_amount": 383901442.6,
      "daily_turnover": 733008672.4000001,
      "buy_ratio": 52.37338343392839,
      "volume_rank": 21,
      "amount_rank": 18,
      "avg_rank": 19.5
    },
    {
      "code": "5880",
      "name": "合庫金",
      "foreign": 3231948,
      "trust": 71000,
      "dealer": 1123375,
      "total": 4426323,
      "close_price": 23.35,
      "daily_volume": 16046027,
      "5day_change": 0.6465500586098619,
      "buy_amount": 103354642.05000001,
      "daily_turnover": 374674730.45000005,
      "buy_ratio": 27.585164851087434,
      "volume_rank": 22,
      "amount_rank": 44,
      "avg_rank": 33.0
    },
    {
      "code": "2884",
      "name": "玉山金",
      "foreign": 6182114,
      "trust": -2478374,
      "dealer": 657473,
      "total": 4361213,
      "close_price": 32.1,
      "daily_volume": 27259557,
      "5day_change": -0.46512101047722865,
      "buy_amount": 139994937.3,
      "daily_turnover": 875031779.7,
      "buy_ratio": 15.998840333318698,
      "volume_rank": 23,
      "amount_rank": 38,
      "avg_rank": 30.5
    },
    {
      "code": "2301",
      "name": "2301",
      "foreign": 5462592,
      "trust": -1699992,
      "dealer": 579639,
      "total": 4342239,
      "close_price": 157.5,
      "daily_volume": 14497036,
      "5day_change": -7.352941176470589,
      "buy_amount": 683902642.5,
      "daily_turnover": 2283283170.0,
      "buy_ratio": 29.952598586359308,
      "volume_rank": 24,
      "amount_rank": 13,
      "avg_rank": 18.5
    },
    {
      "code": "4958",
      "name": "4958",
      "foreign": 3469978,
      "trust": 47667,
      "dealer": 816557,
      "total": 4334202,
      "close_price": 207.5,
      "daily_volume": 22179956,
      "5day_change": 0.24154589371980675,
      "buy_amount": 899346915.0,
      "daily_turnover": 4602340870.0,
      "buy_ratio": 19.541075735226887,
      "volume_rank": 25,
      "amount_rank": 11,
      "avg_rank": 18.0
    },
    {
      "code": "2303",
      "name": "聯電",
      "foreign": 3400267,
      "trust": -479570,
      "dealer": 938366,
      "total": 3859063,
      "close_price": 59.1,
      "daily_volume": 54172278,
      "5day_change": -3.273322504004808,
      "buy_amount": 228070623.3,
      "daily_turnover": 3201581629.8,
      "buy_ratio": 7.123686029965364,
      "volume_rank": 26,
      "amount_rank": 28,
      "avg_rank": 27.0
    },
    {
      "code": "3711",
      "name": "日月光",
      "foreign": 2675055,
      "trust": 959670,
      "dealer": 65935,
      "total": 3700660,
      "close_price": 352.0,
      "daily_volume": 16802165,
      "5day_change": -1.5384615384615385,
      "buy_amount": 1302632320.0,
      "daily_turnover": 5914362080.0,
      "buy_ratio": 22.024899767381168,
      "volume_rank": 27,
      "amount_rank": 6,
      "avg_rank": 16.5
    },
    {
      "code": "8422",
      "name": "可寧衛",
      "foreign": 2804400,
      "trust": -15000,
      "dealer": 761370,
      "total": 3550770,
      "close_price": 30.2,
      "daily_volume": 10067071,
      "5day_change": -0.1652867340844525,
      "buy_amount": 107233254.0,
      "daily_turnover": 304025544.2,
      "buy_ratio": 35.27113298396326,
      "volume_rank": 28,
      "amount_rank": 42,
      "avg_rank": 35.0
    },
    {
      "code": "2208",
      "name": "2208",
      "foreign": 3621905,
      "trust": 0,
      "dealer": -105461,
      "total": 3516444,
      "close_price": 22.1,
      "daily_volume": 7511224,
      "5day_change": 2.3148147739337146,
      "buy_amount": 77713412.4,
      "daily_turnover": 165998050.4,
      "buy_ratio": 46.81585850721534,
      "volume_rank": 29,
      "amount_rank": 46,
      "avg_rank": 37.5
    },
    {
      "code": "6285",
      "name": "6285",
      "foreign": 2934766,
      "trust": -23215,
      "dealer": 604552,
      "total": 3516103,
      "close_price": 180.0,
      "daily_volume": 19491009,
      "5day_change": 3.7463976945244957,
      "buy_amount": 632898540.0,
      "daily_turnover": 3508381620.0,
      "buy_ratio": 18.039615086114832,
      "volume_rank": 30,
      "amount_rank": 15,
      "avg_rank": 22.5
    },
    {
      "code": "6706",
      "name": "6706",
      "foreign": 3503100,
      "trust": -40,
      "dealer": -8223,
      "total": 3494837,
      "close_price": 131.0,
      "daily_volume": 12748345,
      "5day_change": 4.8,
      "buy_amount": 457823647.0,
      "daily_turnover": 1670033195.0,
      "buy_ratio": 27.41404472502117,
      "volume_rank": 31,
      "amount_rank": 17,
      "avg_rank": 24.0
    },
    {
      "code": "3450",
      "name": "3450",
      "foreign": 3251725,
      "trust": -184,
      "dealer": 155522,
      "total": 3407063,
      "close_price": 278.0,
      "daily_volume": 11070453,
      "5day_change": -0.8912655971479502,
      "buy_amount": 947163514.0,
      "daily_turnover": 3077585934.0,
      "buy_ratio": 30.776184136276992,
      "volume_rank": 32,
      "amount_rank": 10,
      "avg_rank": 21.0
    },
    {
      "code": "2881",
      "name": "富邦金",
      "foreign": 3750477,
      "trust": -752000,
      "dealer": 399428,
      "total": 3397905,
      "close_price": 88.8,
      "daily_volume": 13551695,
      "5day_change": -0.7821194952426676,
      "buy_amount": 301733964.0,
      "daily_turnover": 1203390516.0,
      "buy_ratio": 25.07365314818552,
      "volume_rank": 33,
      "amount_rank": 24,
      "avg_rank": 28.5
    },
    {
      "code": "1301",
      "name": "台塑",
      "foreign": 2642357,
      "trust": 10000,
      "dealer": 332047,
      "total": 2984404,
      "close_price": 45.65,
      "daily_volume": 16744226,
      "5day_change": -3.4883673103504673,
      "buy_amount": 136238042.6,
      "daily_turnover": 764373916.9,
      "buy_ratio": 17.823481360081978,
      "volume_rank": 34,
      "amount_rank": 39,
      "avg_rank": 36.5
    },
    {
      "code": "2845",
      "name": "2845",
      "foreign": 2414938,
      "trust": -6000,
      "dealer": 449000,
      "total": 2857938,
      "close_price": 12.45,
      "daily_volume": 5520875,
      "5day_change": 0.0,
      "buy_amount": 35581328.1,
      "daily_turnover": 68734893.75,
      "buy_ratio": 51.76603346389839,
      "volume_rank": 35,
      "amount_rank": 50,
      "avg_rank": 42.5
    },
    {
      "code": "2485",
      "name": "兆赫",
      "foreign": 2780150,
      "trust": 0,
      "dealer": 59000,
      "total": 2839150,
      "close_price": 80.0,
      "daily_volume": 13877241,
      "5day_change": 0.0,
      "buy_amount": 227132000.0,
      "daily_turnover": 1110179280.0,
      "buy_ratio": 20.45903793124296,
      "volume_rank": 36,
      "amount_rank": 29,
      "avg_rank": 32.5
    },
    {
      "code": "2385",
      "name": "2385",
      "foreign": 2350297,
      "trust": 453454,
      "dealer": 7656,
      "total": 2811407,
      "close_price": 123.0,
      "daily_volume": 4316547,
      "5day_change": 0.0,
      "buy_amount": 345803061.0,
      "daily_turnover": 530935281.0,
      "buy_ratio": 65.13092525113244,
      "volume_rank": 37,
      "amount_rank": 20,
      "avg_rank": 28.5
    },
    {
      "code": "1717",
      "name": "1717",
      "foreign": 2562025,
      "trust": 0,
      "dealer": 151968,
      "total": 2713993,
      "close_price": 62.5,
      "daily_volume": 18075601,
      "5day_change": -0.6359324581484054,
      "buy_amount": 169624562.5,
      "daily_turnover": 1129725062.5,
      "buy_ratio": 15.014676413802231,
      "volume_rank": 38,
      "amount_rank": 35,
      "avg_rank": 36.5
    },
    {
      "code": "6505",
      "name": "6505",
      "foreign": 2219496,
      "trust": 10000,
      "dealer": 463470,
      "total": 2692966,
      "close_price": 54.5,
      "daily_volume": 15587426,
      "5day_change": -4.385964912280701,
      "buy_amount": 146766647.0,
      "daily_turnover": 849514717.0,
      "buy_ratio": 17.276527888568648,
      "volume_rank": 39,
      "amount_rank": 37,
      "avg_rank": 38.0
    },
    {
      "code": "6213",
      "name": "6213",
      "foreign": 2522842,
      "trust": -117,
      "dealer": 96532,
      "total": 2619257,
      "close_price": 145.5,
      "daily_volume": 10983249,
      "5day_change": -3.322259136212625,
      "buy_amount": 381101893.5,
      "daily_turnover": 1598062729.5,
      "buy_ratio": 23.847743049438286,
      "volume_rank": 40,
      "amount_rank": 19,
      "avg_rank": 29.5
    },
    {
      "code": "8046",
      "name": "8046",
      "foreign": 1653386,
      "trust": 509783,
      "dealer": 433935,
      "total": 2597104,
      "close_price": 540.0,
      "daily_volume": 11013568,
      "5day_change": -4.761904761904762,
      "buy_amount": 1402436160.0,
      "daily_turnover": 5947326720.0,
      "buy_ratio": 23.58095033326166,
      "volume_rank": 41,
      "amount_rank": 5,
      "avg_rank": 23.0
    },
    {
      "code": "2880",
      "name": "華南金",
      "foreign": 1185600,
      "trust": 636600,
      "dealer": 737822,
      "total": 2560022,
      "close_price": 34.15,
      "daily_volume": 17080938,
      "5day_change": 2.2455088794498614,
      "buy_amount": 87424751.3,
      "daily_turnover": 583314032.6999999,
      "buy_ratio": 14.987596114452264,
      "volume_rank": 42,
      "amount_rank": 45,
      "avg_rank": 43.5
    },
    {
      "code": "2548",
      "name": "2548",
      "foreign": 2399626,
      "trust": 130000,
      "dealer": 11991,
      "total": 2541617,
      "close_price": 123.5,
      "daily_volume": 3900758,
      "5day_change": 6.926406926406926,
      "buy_amount": 313889699.5,
      "daily_turnover": 481743613.0,
      "buy_ratio": 65.15700281842656,
      "volume_rank": 43,
      "amount_rank": 21,
      "avg_rank": 32.0
    },
    {
      "code": "3036",
      "name": "3036",
      "foreign": 2419622,
      "trust": 16676,
      "dealer": 94111,
      "total": 2530409,
      "close_price": 237.5,
      "daily_volume": 7053451,
      "5day_change": -7.2265625,
      "buy_amount": 600972137.5,
      "daily_turnover": 1675194612.5,
      "buy_ratio": 35.87476541624802,
      "volume_rank": 44,
      "amount_rank": 16,
      "avg_rank": 30.0
    },
    {
      "code": "4938",
      "name": "4938",
      "foreign": 2590178,
      "trust": -227904,
      "dealer": 102831,
      "total": 2465105,
      "close_price": 77.4,
      "daily_volume": 7682110,
      "5day_change": -1.023012088980988,
      "buy_amount": 190799127.0,
      "daily_turnover": 594595314.0,
      "buy_ratio": 32.08890526170544,
      "volume_rank": 45,
      "amount_rank": 33,
      "avg_rank": 39.0
    },
    {
      "code": "2812",
      "name": "2812",
      "foreign": 2131100,
      "trust": 0,
      "dealer": 271000,
      "total": 2402100,
      "close_price": 20.6,
      "daily_volume": 5594535,
      "5day_change": 0.48780673887671494,
      "buy_amount": 49483260.0,
      "daily_turnover": 115247421.00000001,
      "buy_ratio": 42.9365443240591,
      "volume_rank": 46,
      "amount_rank": 49,
      "avg_rank": 47.5
    },
    {
      "code": "5871",
      "name": "中租-KY",
      "foreign": 2329520,
      "trust": -34000,
      "dealer": 72579,
      "total": 2368099,
      "close_price": 107.0,
      "daily_volume": 4904459,
      "5day_change": -0.46511627906976744,
      "buy_amount": 253386593.0,
      "daily_turnover": 524777113.0,
      "buy_ratio": 48.28461202346681,
      "volume_rank": 47,
      "amount_rank": 27,
      "avg_rank": 37.0
    },
    {
      "code": "2312",
      "name": "金寶",
      "foreign": 3167918,
      "trust": -974036,
      "dealer": 170424,
      "total": 2364306,
      "close_price": 23.05,
      "daily_volume": 7924667,
      "5day_change": -5.7259774322828845,
      "buy_amount": 54497253.300000004,
      "daily_turnover": 182663574.35,
      "buy_ratio": 29.834767820527986,
      "volume_rank": 48,
      "amount_rank": 47,
      "avg_rank": 47.5
    },
    {
      "code": "2882",
      "name": "國泰金",
      "foreign": 1087798,
      "trust": 739000,
      "dealer": 392780,
      "total": 2219578,
      "close_price": 71.4,
      "daily_volume": 21288556,
      "5day_change": -2.724795583682451,
      "buy_amount": 158477869.20000002,
      "daily_turnover": 1520002898.4,
      "buy_ratio": 10.426155724230428,
      "volume_rank": 49,
      "amount_rank": 36,
      "avg_rank": 42.5
    },
    {
      "code": "2501",
      "name": "2501",
      "foreign": 1972937,
      "trust": 0,
      "dealer": 245000,
      "total": 2217937,
      "close_price": 24.05,
      "daily_volume": 4022059,
      "5day_change": 2.5586288042656937,
      "buy_amount": 53341384.85,
      "daily_turnover": 96730518.95,
      "buy_ratio": 55.14431787300982,
      "volume_rank": 50,
      "amount_rank": 48,
      "avg_rank": 49.0
    }
  ]
}