{
  "2025-10-29": {
    "date": "2025-10-29",
    "predictions": [
      {
        "symbol": "6282",
        "name": "康舒",
        "prev_close": 48.15,
        "direction": "up",
        "target_range": "52-55",
        "target_min": 52,
        "target_max": 55,
        "confidence": 0.85,
        "reasons": [
          "法人買超+16,926張",
          "AI電源供應",
          "GB200需求"
        ],
        "verification": {
          "actual_close": 46.85,
          "actual_change": 0.43,
          "institutional_flow": -18203,
          "result": "partial",
          "notes": "法人昨買今賣誘多陷阱"
        }
      },
      {
        "symbol": "2303",
        "name": "聯電",
        "prev_close": 46.1,
        "direction": "up",
        "target_range": "44-45",
        "target_min": 44,
        "target_max": 45,
        "confidence": 0.75,
        "reasons": [
          "法人買超+31,906張",
          "CoWoS轉單"
        ],
        "verification": {
          "actual_close": 45.6,
          "actual_change": -0.87,
          "institutional_flow": -513,
          "result": "fail",
          "notes": "技術面超買獲利了結"
        }
      },
      {
        "symbol": "2886",
        "name": "兆豐金",
        "prev_close": 41.2,
        "direction": "up",
        "target_range": "39-40",
        "target_min": 39,
        "target_max": 40,
        "confidence": 0.7,
        "reasons": [
          "法人買超+4,368張"
        ],
        "verification": {
          "actual_close": 40.7,
          "actual_change": -0.61,
          "institutional_flow": 2318,
          "result": "fail",
          "notes": "金融產業整體弱勢"
        }
      },
      {
        "symbol": "2324",
        "name": "仁寶",
        "prev_close": 35.2,
        "direction": "up",
        "target_range": "34-35",
        "target_min": 34,
        "target_max": 35,
        "confidence": 0.7,
        "reasons": [
          "法人買超+2,869張"
        ],
        "verification": {
          "actual_close": 34.55,
          "actual_change": 0.14,
          "institutional_flow": -21525,
          "result": "partial",
          "notes": "NB需求疲弱，法人微量試探後大逃殺"
        }
      }
    ],
    "framework": "時事40% + 法人40% + 技術20%",
    "accuracy": 0.0,
    "notes": "從10/27的80%跌至0%，過度依賴短期法人數據"
  },
  "2025-10-30": {
    "date": "2025-10-30",
    "predictions": [
      {
        "symbol": "6770",
        "name": "力積電",
        "prev_close": 32.25,
        "direction": "up",
        "target_range": "31-33",
        "target_min": 31,
        "target_max": 33,
        "confidence": 0.91,
        "reasons": [
          "DRAM Q4+30%漲價",
          "法人買超+39,675張",
          "技術面健康"
        ],
        "verification": {
          "actual_close": 33.05,
          "actual_change": 2.48,
          "institutional_flow": 47367,
          "result": "success",
          "notes": "連2日法人買超+股價上漲，DRAM邏輯最強"
        }
      },
      {
        "symbol": "2330",
        "name": "台積電",
        "prev_close": 1505,
        "direction": "up",
        "target_range": "1480-1520",
        "target_min": 1480,
        "target_max": 1520,
        "confidence": 0.88,
        "reasons": [
          "AI趨勢",
          "法人買超+6,987張",
          "核心資產"
        ],
        "verification": {
          "actual_close": 1505,
          "actual_change": 0.0,
          "institutional_flow": -2162,
          "result": "fail",
          "notes": "川習會避險，法人賣超"
        }
      },
      {
        "symbol": "2344",
        "name": "華邦電",
        "prev_close": 54.0,
        "direction": "up",
        "target_range": "52-55",
        "target_min": 52,
        "target_max": 55,
        "confidence": 0.85,
        "reasons": [
          "DRAM漲價",
          "HBM需求",
          "法人買超+8,325張"
        ],
        "verification": {
          "actual_close": 55.2,
          "actual_change": 2.22,
          "institutional_flow": 619,
          "result": "success",
          "notes": "DRAM邏輯守住，法人續買+619張"
        }
      }
    ],
    "framework": "產業基本面50% + 技術30% + 法人驗證15% + 事件風險5%",
    "accuracy": 0.667,
    "notes": "川習會日DRAM產業邏輯守住（力積電+華邦電成功，台積電避險失敗）",
    "event_risk": "川習會10/30舉行"
  }
}