{
  "date": "2026-04-23",
  "lookback_dates": [
    "2026-04-22",
    "2026-04-21",
    "2026-04-20",
    "2026-04-17",
    "2026-04-16",
    "2026-04-15",
    "2026-04-14"
  ],
  "price_threshold": 5.0,
  "total_scanned": 159,
  "total_filtered": 65,
  "l3_stocks": [],
  "l2_stocks": [
    {
      "code": "2867",
      "name": "三商壽",
      "industry": "其他",
      "category": "",
      "level": "L2",
      "label": "早期佈局",
      "position": "5-10%",
      "confidence": "中",
      "reason": "6天在TOP50+動能-25.2%+漲幅僅-0.1%",
      "days_in_top50": 6,
      "total_buying": 40354340,
      "avg_rank_best": 27.0,
      "latest_5day_change": -0.12641911804776232,
      "latest_close": 7.9,
      "latest_buy_ratio": 60.89159243572947,
      "momentum_pct": -25.2,
      "consecutive_buy": 8,
      "buy_days": 9,
      "sell_days": 1,
      "cumulative_total": 49000,
      "appearances": [
        {
          "date": "2026-04-22",
          "total": 6110000,
          "avg_rank": 31.0,
          "foreign": 6149000,
          "trust": 0,
          "5day_change": -0.12641911804776232,
          "buy_ratio": 60.89159243572947
        },
        {
          "date": "2026-04-21",
          "total": 3776000,
          "avg_rank": 38.5,
          "foreign": 3674000,
          "trust": 0,
          "5day_change": 0.12674561534929774,
          "buy_ratio": 44.57707383148685
        },
        {
          "date": "2026-04-20",
          "total": 5651000,
          "avg_rank": 30.5,
          "foreign": 7056000,
          "trust": 0,
          "5day_change": 2.3376663588899476,
          "buy_ratio": 45.107313259634374
        },
        {
          "date": "2026-04-16",
          "total": 4237340,
          "avg_rank": 39.5,
          "foreign": 3940000,
          "trust": 0,
          "5day_change": 1.4102519741974862,
          "buy_ratio": 43.77657945663957
        },
        {
          "date": "2026-04-15",
          "total": 7260000,
          "avg_rank": 32.0,
          "foreign": 7520000,
          "trust": 0,
          "5day_change": 1.932984717861115,
          "buy_ratio": 60.5811585587492
        },
        {
          "date": "2026-04-14",
          "total": 13320000,
          "avg_rank": 27.0,
          "foreign": 12894000,
          "trust": 0,
          "5day_change": 1.932984717861115,
          "buy_ratio": 110.85129299045332
        }
      ]
    },
    {
      "code": "1303",
      "name": "南亞",
      "industry": "石化塑膠",
      "category": "塑化",
      "level": "L2",
      "label": "早期佈局",
      "position": "5-10%",
      "confidence": "中",
      "reason": "5天在TOP50+動能-73.9%+漲幅僅+1.0%",
      "days_in_top50": 5,
      "total_buying": 115256062,
      "avg_rank_best": 3.5,
      "latest_5day_change": 1.0169508766993292,
      "latest_close": 89.4,
      "latest_buy_ratio": 24.3329995205888,
      "momentum_pct": -73.9,
      "consecutive_buy": 2,
      "buy_days": 7,
      "sell_days": 3,
      "cumulative_total": 111000,
      "appearances": [
        {
          "date": "2026-04-22",
          "total": 14365981,
          "avg_rank": 6.0,
          "foreign": 14199991,
          "trust": -106333,
          "5day_change": 1.0169508766993292,
          "buy_ratio": 24.3329995205888
        },
        {
          "date": "2026-04-21",
          "total": 21666980,
          "avg_rank": 7.0,
          "foreign": 21401462,
          "trust": 144300,
          "5day_change": -0.6741555889001053,
          "buy_ratio": 37.44230993914613
        },
        {
          "date": "2026-04-16",
          "total": 13045206,
          "avg_rank": 10.0,
          "foreign": 20287888,
          "trust": -8725076,
          "5day_change": 6.220661081686999,
          "buy_ratio": 14.098462670410921
        },
        {
          "date": "2026-04-15",
          "total": 29650021,
          "avg_rank": 3.5,
          "foreign": 37368949,
          "trust": -5550559,
          "5day_change": 3.9953015121531954,
          "buy_ratio": 22.809613064229325
        },
        {
          "date": "2026-04-14",
          "total": 36527874,
          "avg_rank": 6.5,
          "foreign": 35893992,
          "trust": 1006430,
          "5day_change": 3.9953015121531954,
          "buy_ratio": 27.9641759358479
        }
      ]
    },
    {
      "code": "6116",
      "name": "6116",
      "industry": "其他",
      "category": "",
      "level": "L2",
      "label": "早期佈局",
      "position": "5-10%",
      "confidence": "中",
      "reason": "5天在TOP50+動能-49.6%+漲幅僅-1.0%",
      "days_in_top50": 5,
      "total_buying": 44571858,
      "avg_rank_best": 19.5,
      "latest_5day_change": -1.0067024959492843,
      "latest_close": 8.85,
      "latest_buy_ratio": 21.57743985792365,
      "momentum_pct": -49.6,
      "consecutive_buy": 1,
      "buy_days": 7,
      "sell_days": 3,
      "cumulative_total": 38000,
      "appearances": [
        {
          "date": "2026-04-22",
          "total": 2500909,
          "avg_rank": 41.0,
          "foreign": 2614000,
          "trust": 0,
          "5day_change": -1.0067024959492843,
          "buy_ratio": 21.57743985792365
        },
        {
          "date": "2026-04-20",
          "total": 2141756,
          "avg_rank": 44.5,
          "foreign": 2114000,
          "trust": 0,
          "5day_change": 6.690136903746508,
          "buy_ratio": 13.253020696373977
        },
        {
          "date": "2026-04-16",
          "total": 17501060,
          "avg_rank": 19.5,
          "foreign": 16771200,
          "trust": 0,
          "5day_change": 5.942862374441964,
          "buy_ratio": 30.707588782281327
        },
        {
          "date": "2026-04-15",
          "total": 10853990,
          "avg_rank": 26.0,
          "foreign": 10574300,
          "trust": 0,
          "5day_change": 6.428571266381912,
          "buy_ratio": 38.50130123805528
        },
        {
          "date": "2026-04-14",
          "total": 11574143,
          "avg_rank": 28.0,
          "foreign": 10539290,
          "trust": 0,
          "5day_change": 6.428571266381912,
          "buy_ratio": 40.99410866612684
        }
      ]
    },
    {
      "code": "3045",
      "name": "3045",
      "industry": "電信服務",
      "category": "電信",
      "level": "L2",
      "label": "早期佈局",
      "position": "5-10%",
      "confidence": "中",
      "reason": "5天在TOP50+動能-23.5%+漲幅僅+2.7%",
      "days_in_top50": 5,
      "total_buying": 22013082,
      "avg_rank_best": 12.0,
      "latest_5day_change": 2.727272727272727,
      "latest_close": 113.0,
      "latest_buy_ratio": 14.600816090142732,
      "momentum_pct": -23.5,
      "consecutive_buy": 1,
      "buy_days": 8,
      "sell_days": 2,
      "cumulative_total": 31000,
      "appearances": [
        {
          "date": "2026-04-22",
          "total": 1985599,
          "avg_rank": 32.5,
          "foreign": 1192058,
          "trust": 595953,
          "5day_change": 2.727272727272727,
          "buy_ratio": 14.600816090142732
        },
        {
          "date": "2026-04-17",
          "total": 8189809,
          "avg_rank": 12.0,
          "foreign": 9525003,
          "trust": -1006022,
          "5day_change": 2.272727272727273,
          "buy_ratio": 42.920521917333254
        },
        {
          "date": "2026-04-16",
          "total": 4798722,
          "avg_rank": 22.0,
          "foreign": 5084326,
          "trust": -202604,
          "5day_change": 0.0,
          "buy_ratio": 61.243137984610094
        },
        {
          "date": "2026-04-15",
          "total": 2843508,
          "avg_rank": 36.5,
          "foreign": 3623123,
          "trust": -477615,
          "5day_change": 0.45662100456621,
          "buy_ratio": 37.616241598379524
        },
        {
          "date": "2026-04-14",
          "total": 4195444,
          "avg_rank": 26.5,
          "foreign": 4502168,
          "trust": -149467,
          "5day_change": 0.45662100456621,
          "buy_ratio": 57.15090587880959
        }
      ]
    },
    {
      "code": "1301",
      "name": "台塑",
      "industry": "石化塑膠",
      "category": "塑化龍頭",
      "level": "L2",
      "label": "早期佈局",
      "position": "5-10%",
      "confidence": "中",
      "reason": "4天在TOP50+動能-84.4%+漲幅僅-0.8%",
      "days_in_top50": 4,
      "total_buying": 92091833,
      "avg_rank_best": 4.5,
      "latest_5day_change": -0.7648139904717176,
      "latest_close": 51.9,
      "latest_buy_ratio": 13.819343677413066,
      "momentum_pct": -84.4,
      "consecutive_buy": 2,
      "buy_days": 8,
      "sell_days": 2,
      "cumulative_total": 149000,
      "appearances": [
        {
          "date": "2026-04-22",
          "total": 2092551,
          "avg_rank": 36.5,
          "foreign": 2090505,
          "trust": -41881,
          "5day_change": -0.7648139904717176,
          "buy_ratio": 13.819343677413066
        },
        {
          "date": "2026-04-16",
          "total": 19878409,
          "avg_rank": 6.5,
          "foreign": 19969897,
          "trust": 1252,
          "5day_change": 14.97889925223888,
          "buy_ratio": 49.31977060104449
        },
        {
          "date": "2026-04-15",
          "total": 6810982,
          "avg_rank": 18.5,
          "foreign": 6379305,
          "trust": 1197886,
          "5day_change": 10.805081338315393,
          "buy_ratio": 14.912627775513714
        },
        {
          "date": "2026-04-14",
          "total": 63309891,
          "avg_rank": 4.5,
          "foreign": 62667781,
          "trust": -2338,
          "5day_change": 10.805081338315393,
          "buy_ratio": 137.82763891508583
        }
      ]
    },
    {
      "code": "2327",
      "name": "國巨",
      "industry": "被動元件/電子零組件",
      "category": "MLCC龍頭",
      "level": "L2",
      "label": "早期佈局",
      "position": "5-10%",
      "confidence": "中",
      "reason": "4天在TOP50+動能-92.4%+漲幅僅+3.5%",
      "days_in_top50": 4,
      "total_buying": 36813685,
      "avg_rank_best": 6.5,
      "latest_5day_change": 3.5256410256410255,
      "latest_close": 323.0,
      "latest_buy_ratio": 19.935992265604938,
      "momentum_pct": -92.4,
      "consecutive_buy": 0,
      "buy_days": 8,
      "sell_days": 2,
      "cumulative_total": 90000,
      "appearances": [
        {
          "date": "2026-04-21",
          "total": 6532609,
          "avg_rank": 12.5,
          "foreign": 9201951,
          "trust": -2348014,
          "5day_change": 3.5256410256410255,
          "buy_ratio": 19.935992265604938
        },
        {
          "date": "2026-04-16",
          "total": 8918766,
          "avg_rank": 9.0,
          "foreign": 8172232,
          "trust": 1218293,
          "5day_change": 15.452930728241562,
          "buy_ratio": 13.271596593233582
        },
        {
          "date": "2026-04-15",
          "total": 6465863,
          "avg_rank": 12.0,
          "foreign": 4641533,
          "trust": 1542059,
          "5day_change": 18.60036832412523,
          "buy_ratio": 8.662990020803809
        },
        {
          "date": "2026-04-14",
          "total": 14896447,
          "avg_rank": 6.5,
          "foreign": 10187930,
          "trust": 3707827,
          "5day_change": 18.60036832412523,
          "buy_ratio": 19.58770383023451
        }
      ]
    },
    {
      "code": "2884",
      "name": "玉山金",
      "industry": "其他",
      "category": "",
      "level": "L2",
      "label": "早期佈局",
      "position": "5-10%",
      "confidence": "中",
      "reason": "4天在TOP50+動能-14.9%+漲幅僅+0.3%",
      "days_in_top50": 4,
      "total_buying": 33705167,
      "avg_rank_best": 14.5,
      "latest_5day_change": 0.3034854986515422,
      "latest_close": 33.05,
      "latest_buy_ratio": 23.86083470820976,
      "momentum_pct": -14.9,
      "consecutive_buy": 3,
      "buy_days": 7,
      "sell_days": 3,
      "cumulative_total": 24000,
      "appearances": [
        {
          "date": "2026-04-22",
          "total": 10111829,
          "avg_rank": 14.5,
          "foreign": 20420372,
          "trust": -10525565,
          "5day_change": 0.3034854986515422,
          "buy_ratio": 23.86083470820976
        },
        {
          "date": "2026-04-20",
          "total": 5546989,
          "avg_rank": 22.0,
          "foreign": 16655751,
          "trust": -11701512,
          "5day_change": 2.496097522946208,
          "buy_ratio": 14.346547106180358
        },
        {
          "date": "2026-04-15",
          "total": 7503345,
          "avg_rank": 20.5,
          "foreign": 9899161,
          "trust": -1501479,
          "5day_change": 1.5408320130797677,
          "buy_ratio": 19.842216281319704
        },
        {
          "date": "2026-04-14",
          "total": 10543004,
          "avg_rank": 21.0,
          "foreign": 12433000,
          "trust": -1454303,
          "5day_change": 1.5408320130797677,
          "buy_ratio": 27.73676356000475
        }
      ]
    },
    {
      "code": "3576",
      "name": "3576",
      "industry": "其他",
      "category": "",
      "level": "L2",
      "label": "早期佈局",
      "position": "5-10%",
      "confidence": "中",
      "reason": "4天在TOP50+動能-83.1%+漲幅僅-4.7%",
      "days_in_top50": 4,
      "total_buying": 25936686,
      "avg_rank_best": 22.5,
      "latest_5day_change": -4.733723403066678,
      "latest_close": 16.1,
      "latest_buy_ratio": 21.825108079720867,
      "momentum_pct": -83.1,
      "consecutive_buy": 1,
      "buy_days": 7,
      "sell_days": 3,
      "cumulative_total": 27000,
      "appearances": [
        {
          "date": "2026-04-22",
          "total": 5905900,
          "avg_rank": 26.0,
          "foreign": 5934900,
          "trust": 0,
          "5day_change": -4.733723403066678,
          "buy_ratio": 21.825108079720867
        },
        {
          "date": "2026-04-20",
          "total": 6519674,
          "avg_rank": 24.0,
          "foreign": 6525674,
          "trust": 0,
          "5day_change": 0.5847975394087778,
          "buy_ratio": 18.388520409077042
        },
        {
          "date": "2026-04-15",
          "total": 10619952,
          "avg_rank": 22.5,
          "foreign": 10114000,
          "trust": 0,
          "5day_change": -20.65727594428536,
          "buy_ratio": 22.189471361662438
        },
        {
          "date": "2026-04-14",
          "total": 2891160,
          "avg_rank": 46.5,
          "foreign": 2874160,
          "trust": 0,
          "5day_change": -20.65727594428536,
          "buy_ratio": 6.018634459698719
        }
      ]
    },
    {
      "code": "1326",
      "name": "台化",
      "industry": "石化塑膠",
      "category": "化纖",
      "level": "L2",
      "label": "早期佈局",
      "position": "5-10%",
      "confidence": "中",
      "reason": "3天在TOP50+動能-93.8%+漲幅僅+1.1%",
      "days_in_top50": 3,
      "total_buying": 69961217,
      "avg_rank_best": 6.5,
      "latest_5day_change": 1.1010995568765245,
      "latest_close": 50.5,
      "latest_buy_ratio": 10.28683135212603,
      "momentum_pct": -93.8,
      "consecutive_buy": 0,
      "buy_days": 6,
      "sell_days": 4,
      "cumulative_total": 108000,
      "appearances": [
        {
          "date": "2026-04-20",
          "total": 2078240,
          "avg_rank": 40.0,
          "foreign": 2233535,
          "trust": 2000,
          "5day_change": 1.1010995568765245,
          "buy_ratio": 10.28683135212603
        },
        {
          "date": "2026-04-16",
          "total": 8569272,
          "avg_rank": 17.5,
          "foreign": 8197107,
          "trust": -10000,
          "5day_change": 14.25438644189622,
          "buy_ratio": 25.207730670551122
        },
        {
          "date": "2026-04-14",
          "total": 59313705,
          "avg_rank": 6.5,
          "foreign": 59406391,
          "trust": 314000,
          "5day_change": 11.75167013541922,
          "buy_ratio": 70.57807855681212
        }
      ]
    },
    {
      "code": "2002",
      "name": "中鋼",
      "industry": "鋼鐵/原物料",
      "category": "鋼鐵龍頭",
      "level": "L2",
      "label": "早期佈局",
      "position": "5-10%",
      "confidence": "中",
      "reason": "3天在TOP50+動能-87.6%+漲幅僅+0.2%",
      "days_in_top50": 3,
      "total_buying": 57099669,
      "avg_rank_best": 12.0,
      "latest_5day_change": 0.24938227586940379,
      "latest_close": 20.1,
      "latest_buy_ratio": 30.804996017297714,
      "momentum_pct": -87.6,
      "consecutive_buy": 0,
      "buy_days": 8,
      "sell_days": 2,
      "cumulative_total": 107000,
      "appearances": [
        {
          "date": "2026-04-17",
          "total": 8019334,
          "avg_rank": 25.0,
          "foreign": 8304587,
          "trust": -210737,
          "5day_change": 0.24938227586940379,
          "buy_ratio": 30.804996017297714
        },
        {
          "date": "2026-04-16",
          "total": 12953174,
          "avg_rank": 21.5,
          "foreign": 13080293,
          "trust": 73317,
          "5day_change": -1.2376237156320813,
          "buy_ratio": 28.15655145329263
        },
        {
          "date": "2026-04-14",
          "total": 36127161,
          "avg_rank": 12.0,
          "foreign": 34918288,
          "trust": 93437,
          "5day_change": 0.7518777583654205,
          "buy_ratio": 88.21005702973179
        }
      ]
    },
    {
      "code": "2890",
      "name": "永豐金",
      "industry": "其他",
      "category": "",
      "level": "L2",
      "label": "早期佈局",
      "position": "5-10%",
      "confidence": "中",
      "reason": "3天在TOP50+動能-153.3%+漲幅僅+0.6%",
      "days_in_top50": 3,
      "total_buying": 20265773,
      "avg_rank_best": 19.0,
      "latest_5day_change": 0.6042319400583107,
      "latest_close": 33.3,
      "latest_buy_ratio": 24.073499594002694,
      "momentum_pct": -153.3,
      "consecutive_buy": 0,
      "buy_days": 6,
      "sell_days": 4,
      "cumulative_total": 12000,
      "appearances": [
        {
          "date": "2026-04-16",
          "total": 4402337,
          "avg_rank": 33.5,
          "foreign": 8955479,
          "trust": -4237886,
          "5day_change": 0.6042319400583107,
          "buy_ratio": 24.073499594002694
        },
        {
          "date": "2026-04-15",
          "total": 4889354,
          "avg_rank": 30.5,
          "foreign": 8159746,
          "trust": -1867436,
          "5day_change": 1.834857676214803,
          "buy_ratio": 27.378953218641982
        },
        {
          "date": "2026-04-14",
          "total": 10974082,
          "avg_rank": 19.0,
          "foreign": 13676723,
          "trust": -2322065,
          "5day_change": 1.834857676214803,
          "buy_ratio": 61.159877770328364
        }
      ]
    },
    {
      "code": "2801",
      "name": "彰銀",
      "industry": "金融產業",
      "category": "銀行",
      "level": "L2",
      "label": "早期佈局",
      "position": "5-10%",
      "confidence": "中",
      "reason": "3天在TOP50+動能-65.8%+漲幅僅+2.1%",
      "days_in_top50": 3,
      "total_buying": 16556305,
      "avg_rank_best": 23.0,
      "latest_5day_change": 2.1276632201221948,
      "latest_close": 21.6,
      "latest_buy_ratio": 15.309302542161499,
      "momentum_pct": -65.8,
      "consecutive_buy": 0,
      "buy_days": 7,
      "sell_days": 3,
      "cumulative_total": 29000,
      "appearances": [
        {
          "date": "2026-04-20",
          "total": 2585813,
          "avg_rank": 38.5,
          "foreign": 5715567,
          "trust": -3129754,
          "5day_change": 2.1276632201221948,
          "buy_ratio": 15.309302542161499
        },
        {
          "date": "2026-04-17",
          "total": 5561559,
          "avg_rank": 30.5,
          "foreign": 6123929,
          "trust": -627000,
          "5day_change": 2.1276632201221948,
          "buy_ratio": 29.16110960685694
        },
        {
          "date": "2026-04-15",
          "total": 8408933,
          "avg_rank": 23.0,
          "foreign": 9087819,
          "trust": -526000,
          "5day_change": 2.392344541273063,
          "buy_ratio": 44.84675051530974
        }
      ]
    },
    {
      "code": "6505",
      "name": "6505",
      "industry": "其他",
      "category": "",
      "level": "L2",
      "label": "早期佈局",
      "position": "5-10%",
      "confidence": "中",
      "reason": "2天在TOP50+動能-90.2%+漲幅僅+4.6%",
      "days_in_top50": 2,
      "total_buying": 11497613,
      "avg_rank_best": 23.5,
      "latest_5day_change": 4.554075287356364,
      "latest_close": 55.1,
      "latest_buy_ratio": 50.55127234243422,
      "momentum_pct": -90.2,
      "consecutive_buy": 0,
      "buy_days": 6,
      "sell_days": 4,
      "cumulative_total": 10000,
      "appearances": [
        {
          "date": "2026-04-16",
          "total": 4841584,
          "avg_rank": 27.5,
          "foreign": 4762877,
          "trust": -12701,
          "5day_change": 4.554075287356364,
          "buy_ratio": 50.55127234243422
        },
        {
          "date": "2026-04-14",
          "total": 6656029,
          "avg_rank": 23.5,
          "foreign": 6116821,
          "trust": -25380,
          "5day_change": 0.1841662803378206,
          "buy_ratio": 48.60123111873033
        }
      ]
    },
    {
      "code": "2845",
      "name": "2845",
      "industry": "其他",
      "category": "",
      "level": "L2",
      "label": "早期佈局",
      "position": "5-10%",
      "confidence": "中",
      "reason": "2天在TOP50+動能-30.1%+漲幅僅+0.4%",
      "days_in_top50": 2,
      "total_buying": 8644102,
      "avg_rank_best": 32.5,
      "latest_5day_change": 0.3952584367008265,
      "latest_close": 12.7,
      "latest_buy_ratio": 64.5392527480019,
      "momentum_pct": -30.1,
      "consecutive_buy": 0,
      "buy_days": 8,
      "sell_days": 2,
      "cumulative_total": 12000,
      "appearances": [
        {
          "date": "2026-04-16",
          "total": 5150102,
          "avg_rank": 32.5,
          "foreign": 4760102,
          "trust": -50000,
          "5day_change": 0.3952584367008265,
          "buy_ratio": 64.5392527480019
        },
        {
          "date": "2026-04-14",
          "total": 3494000,
          "avg_rank": 42.5,
          "foreign": 2971000,
          "trust": -24000,
          "5day_change": 0.0,
          "buy_ratio": 62.70656915023445
        }
      ]
    }
  ],
  "l1_stocks": [
    {
      "code": "2330",
      "name": "台積電",
      "industry": "半導體產業",
      "category": "晶圓代工龍頭",
      "level": "L1",
      "label": "態度轉變",
      "position": "觀察",
      "confidence": "低",
      "reason": "3天在TOP50+漲幅-0.2%尚未反映",
      "days_in_top50": 3,
      "total_buying": 27983665,
      "avg_rank_best": 5.0,
      "latest_5day_change": -0.24330900243309003,
      "latest_close": 2050.0,
      "latest_buy_ratio": 10.972523642661681,
      "momentum_pct": -156.7,
      "consecutive_buy": 0,
      "buy_days": 5,
      "sell_days": 5,
      "cumulative_total": 11000,
      "appearances": [
        {
          "date": "2026-04-21",
          "total": 2829098,
          "avg_rank": 18.5,
          "foreign": 2210163,
          "trust": 696158,
          "5day_change": -0.24330900243309003,
          "buy_ratio": 10.972523642661681
        },
        {
          "date": "2026-04-15",
          "total": 4931287,
          "avg_rank": 12.0,
          "foreign": 4825960,
          "trust": -138422,
          "5day_change": 6.666666666666667,
          "buy_ratio": 12.223229735158775
        },
        {
          "date": "2026-04-14",
          "total": 20223280,
          "avg_rank": 5.0,
          "foreign": 18954661,
          "trust": 615130,
          "5day_change": 6.666666666666667,
          "buy_ratio": 46.52209964673553
        }
      ]
    }
  ]
}