{
  "date": "2026-07-15",
  "lookback_dates": [
    "2026-07-15",
    "2026-07-14",
    "2026-07-13",
    "2026-07-12",
    "2026-07-11",
    "2026-07-10",
    "2026-07-09"
  ],
  "leader_trends": {
    "Micron": {
      "cumulative": 980.71,
      "consecutive_up": 1,
      "latest_change": 983.12,
      "signal_level": "strong",
      "days_tracked": 7
    },
    "NVIDIA": {
      "cumulative": 223.36,
      "consecutive_up": 1,
      "latest_change": 211.8,
      "signal_level": "strong",
      "days_tracked": 7
    },
    "Apple": {
      "cumulative": 316.43,
      "consecutive_up": 2,
      "latest_change": 314.86,
      "signal_level": "strong",
      "days_tracked": 7
    },
    "AMD": {
      "cumulative": 555.95,
      "consecutive_up": 1,
      "latest_change": 548.13,
      "signal_level": "strong",
      "days_tracked": 7
    },
    "Tesla": {
      "cumulative": 394.87,
      "consecutive_up": 1,
      "latest_change": 396.18,
      "signal_level": "strong",
      "days_tracked": 7
    },
    "Super Micro": {
      "cumulative": 33.66,
      "consecutive_up": 1,
      "latest_change": 27.65,
      "signal_level": "strong",
      "days_tracked": 7
    },
    "Broadcom": {
      "cumulative": 392.32,
      "consecutive_up": 1,
      "latest_change": 389.11,
      "signal_level": "strong",
      "days_tracked": 7
    },
    "Lam Research": {
      "cumulative": 346.03,
      "consecutive_up": 1,
      "latest_change": 346.1,
      "signal_level": "strong",
      "days_tracked": 7
    },
    "Applied Materials": {
      "cumulative": 604.32,
      "consecutive_up": 1,
      "latest_change": 595.7,
      "signal_level": "strong",
      "days_tracked": 7
    },
    "Western Digital": {
      "cumulative": 569.51,
      "consecutive_up": 1,
      "latest_change": 563.32,
      "signal_level": "strong",
      "days_tracked": 7
    },
    "Dell": {
      "cumulative": 453.3,
      "consecutive_up": 1,
      "latest_change": 457.54,
      "signal_level": "strong",
      "days_tracked": 7
    },
    "ASML": {
      "cumulative": 1773.76,
      "consecutive_up": 1,
      "latest_change": 1775.64,
      "signal_level": "strong",
      "days_tracked": 7
    }
  },
  "preposition_candidates": [
    {
      "code": "2344",
      "name": "華邦電",
      "tw_industry": "DRAM/記憶體",
      "us_leader": "Micron",
      "signal_level": "strong",
      "leader_cumulative": 980.71,
      "leader_consecutive_up": 1,
      "maturity": "mature",
      "tw_5d_change": null,
      "in_top50": false,
      "score": 73,
      "chip_data": {
        "cumulative_total": -138515,
        "buy_days": 1,
        "sell_days": 9,
        "momentum_pct": 71.47523034526273,
        "consecutive_buy": 0,
        "cumulative_foreign": -48577,
        "reversal_level": "Level 3",
        "exclusion_reason": "反轉Level 3排除｜累計-138,515為負",
        "passed": false
      }
    },
    {
      "code": "2337",
      "name": "旺宏",
      "tw_industry": "DRAM/記憶體",
      "us_leader": "Micron",
      "signal_level": "strong",
      "leader_cumulative": 980.71,
      "leader_consecutive_up": 1,
      "maturity": "mature",
      "tw_5d_change": null,
      "in_top50": false,
      "score": 73,
      "chip_data": {
        "cumulative_total": -114813,
        "buy_days": 1,
        "sell_days": 9,
        "momentum_pct": 87.06732897260612,
        "consecutive_buy": 0,
        "cumulative_foreign": -109849,
        "reversal_level": "Level 3",
        "exclusion_reason": "反轉Level 3排除｜累計-114,813為負",
        "passed": false
      }
    },
    {
      "code": "5347",
      "name": "世界",
      "tw_industry": "DRAM/記憶體",
      "us_leader": "Micron",
      "signal_level": "strong",
      "leader_cumulative": 980.71,
      "leader_consecutive_up": 1,
      "maturity": "mature",
      "tw_5d_change": null,
      "in_top50": false,
      "score": 73,
      "chip_data": {
        "cumulative_total": null,
        "buy_days": null,
        "sell_days": null,
        "momentum_pct": null,
        "consecutive_buy": null,
        "cumulative_foreign": null,
        "reversal_level": "unknown",
        "exclusion_reason": "數據不足無法評分",
        "passed": false
      }
    },
    {
      "code": "6770",
      "name": "力積電",
      "tw_industry": "DRAM/記憶體",
      "us_leader": "Micron",
      "signal_level": "strong",
      "leader_cumulative": 980.71,
      "leader_consecutive_up": 1,
      "maturity": "mature",
      "tw_5d_change": null,
      "in_top50": false,
      "score": 73,
      "chip_data": {
        "cumulative_total": -124151,
        "buy_days": 1,
        "sell_days": 9,
        "momentum_pct": 61.96395414771906,
        "consecutive_buy": 0,
        "cumulative_foreign": -118632,
        "reversal_level": "Level 4",
        "exclusion_reason": "反轉Level 4排除｜累計-124,151為負",
        "passed": false
      }
    },
    {
      "code": "4967",
      "name": "十銓",
      "tw_industry": "DRAM/記憶體",
      "us_leader": "Micron",
      "signal_level": "strong",
      "leader_cumulative": 980.71,
      "leader_consecutive_up": 1,
      "maturity": "mature",
      "tw_5d_change": null,
      "in_top50": false,
      "score": 73,
      "chip_data": {
        "cumulative_total": -1109,
        "buy_days": 5,
        "sell_days": 5,
        "momentum_pct": -17.878192534381142,
        "consecutive_buy": 2,
        "cumulative_foreign": -1339,
        "reversal_level": "Level 0",
        "exclusion_reason": "累計-1,109為負",
        "passed": false
      }
    },
    {
      "code": "2451",
      "name": "創見",
      "tw_industry": "DRAM/記憶體",
      "us_leader": "Micron",
      "signal_level": "strong",
      "leader_cumulative": 980.71,
      "leader_consecutive_up": 1,
      "maturity": "mature",
      "tw_5d_change": null,
      "in_top50": false,
      "score": 73,
      "chip_data": {
        "cumulative_total": -6015,
        "buy_days": 2,
        "sell_days": 8,
        "momentum_pct": 19.964082609997018,
        "consecutive_buy": 0,
        "cumulative_foreign": -7676,
        "reversal_level": "Level 4",
        "exclusion_reason": "反轉Level 4排除｜累計-6,015為負",
        "passed": false
      }
    },
    {
      "code": "3260",
      "name": "威剛",
      "tw_industry": "DRAM/記憶體",
      "us_leader": "Micron",
      "signal_level": "strong",
      "leader_cumulative": 980.71,
      "leader_consecutive_up": 1,
      "maturity": "mature",
      "tw_5d_change": null,
      "in_top50": false,
      "score": 73,
      "chip_data": {
        "cumulative_total": null,
        "buy_days": null,
        "sell_days": null,
        "momentum_pct": null,
        "consecutive_buy": null,
        "cumulative_foreign": null,
        "reversal_level": "unknown",
        "exclusion_reason": "數據不足無法評分",
        "passed": false
      }
    },
    {
      "code": "6239",
      "name": "力成",
      "tw_industry": "DRAM/記憶體",
      "us_leader": "Micron",
      "signal_level": "strong",
      "leader_cumulative": 980.71,
      "leader_consecutive_up": 1,
      "maturity": "mature",
      "tw_5d_change": null,
      "in_top50": false,
      "score": 73,
      "chip_data": {
        "cumulative_total": 3639,
        "buy_days": 6,
        "sell_days": 4,
        "momentum_pct": -152.12472043152218,
        "consecutive_buy": 1,
        "cumulative_foreign": 17976,
        "reversal_level": "unknown",
        "exclusion_reason": "動能-152%>100%排除｜數據不足無法評分",
        "passed": false
      }
    },
    {
      "code": "2449",
      "name": "京元電",
      "tw_industry": "DRAM/記憶體",
      "us_leader": "Micron",
      "signal_level": "strong",
      "leader_cumulative": 980.71,
      "leader_consecutive_up": 1,
      "maturity": "mature",
      "tw_5d_change": null,
      "in_top50": false,
      "score": 73,
      "chip_data": {
        "cumulative_total": -6504,
        "buy_days": 4,
        "sell_days": 6,
        "momentum_pct": -219.494065459777,
        "consecutive_buy": 0,
        "cumulative_foreign": -8981,
        "reversal_level": "Level 4",
        "exclusion_reason": "反轉Level 4排除｜累計-6,504為負",
        "passed": false
      }
    },
    {
      "code": "8299",
      "name": "群聯",
      "tw_industry": "DRAM/記憶體",
      "us_leader": "Micron",
      "signal_level": "strong",
      "leader_cumulative": 980.71,
      "leader_consecutive_up": 1,
      "maturity": "mature",
      "tw_5d_change": null,
      "in_top50": false,
      "score": 73,
      "chip_data": {
        "cumulative_total": null,
        "buy_days": null,
        "sell_days": null,
        "momentum_pct": null,
        "consecutive_buy": null,
        "cumulative_foreign": null,
        "reversal_level": "unknown",
        "exclusion_reason": "數據不足無法評分",
        "passed": false
      }
    },
    {
      "code": "5289",
      "name": "宜鼎",
      "tw_industry": "DRAM/記憶體",
      "us_leader": "Micron",
      "signal_level": "strong",
      "leader_cumulative": 980.71,
      "leader_consecutive_up": 1,
      "maturity": "mature",
      "tw_5d_change": null,
      "in_top50": false,
      "score": 73,
      "chip_data": {}
    },
    {
      "code": "3037",
      "name": "欣興",
      "tw_industry": "DRAM/記憶體",
      "us_leader": "Micron",
      "signal_level": "strong",
      "leader_cumulative": 980.71,
      "leader_consecutive_up": 1,
      "maturity": "mature",
      "tw_5d_change": null,
      "in_top50": false,
      "score": 73,
      "chip_data": {}
    },
    {
      "code": "6488",
      "name": "環球晶",
      "tw_industry": "DRAM/記憶體",
      "us_leader": "Micron",
      "signal_level": "strong",
      "leader_cumulative": 980.71,
      "leader_consecutive_up": 1,
      "maturity": "mature",
      "tw_5d_change": null,
      "in_top50": false,
      "score": 73,
      "chip_data": {}
    },
    {
      "code": "5351",
      "name": "鈺創",
      "tw_industry": "DRAM/記憶體",
      "us_leader": "Micron",
      "signal_level": "strong",
      "leader_cumulative": 980.71,
      "leader_consecutive_up": 1,
      "maturity": "mature",
      "tw_5d_change": null,
      "in_top50": false,
      "score": 73,
      "chip_data": {}
    },
    {
      "code": "8096",
      "name": "擎亞",
      "tw_industry": "DRAM/記憶體",
      "us_leader": "Micron",
      "signal_level": "strong",
      "leader_cumulative": 980.71,
      "leader_consecutive_up": 1,
      "maturity": "mature",
      "tw_5d_change": null,
      "in_top50": false,
      "score": 73,
      "chip_data": {}
    }
  ],
  "already_in_top50": [
    {
      "code": "2382",
      "name": "廣達",
      "tw_industry": "AI伺服器",
      "us_leader": "NVIDIA",
      "leader_cumulative": 223.36,
      "tw_5d_change": 0.0
    },
    {
      "code": "3231",
      "name": "緯創",
      "tw_industry": "AI伺服器",
      "us_leader": "NVIDIA",
      "leader_cumulative": 223.36,
      "tw_5d_change": -8.360128617363344
    },
    {
      "code": "3711",
      "name": "日月光",
      "tw_industry": "AI伺服器",
      "us_leader": "NVIDIA",
      "leader_cumulative": 223.36,
      "tw_5d_change": -0.7331378299120235
    },
    {
      "code": "2367",
      "name": "燿華",
      "tw_industry": "AI伺服器",
      "us_leader": "NVIDIA",
      "leader_cumulative": 223.36,
      "tw_5d_change": -5.294119143018536
    },
    {
      "code": "2301",
      "name": "光寶科",
      "tw_industry": "AI伺服器",
      "us_leader": "NVIDIA",
      "leader_cumulative": 223.36,
      "tw_5d_change": -0.8928571428571428
    },
    {
      "code": "2303",
      "name": "聯電",
      "tw_industry": "AI伺服器",
      "us_leader": "NVIDIA",
      "leader_cumulative": 223.36,
      "tw_5d_change": -2.5806451612903225
    },
    {
      "code": "2353",
      "name": "宏碁",
      "tw_industry": "蘋果供應鏈",
      "us_leader": "Apple",
      "leader_cumulative": 316.43,
      "tw_5d_change": -1.2158100526660096
    },
    {
      "code": "2371",
      "name": "大同",
      "tw_industry": "電動車",
      "us_leader": "Tesla",
      "leader_cumulative": 394.87,
      "tw_5d_change": -0.17761718557052458
    },
    {
      "code": "2347",
      "name": "聯強",
      "tw_industry": "電動車",
      "us_leader": "Tesla",
      "leader_cumulative": 394.87,
      "tw_5d_change": -8.981384779350062
    },
    {
      "code": "3042",
      "name": "晶技",
      "tw_industry": "網通",
      "us_leader": "Broadcom",
      "leader_cumulative": 392.32,
      "tw_5d_change": -11.904761904761903
    }
  ],
  "already_moved_count": 21
}